{
"type": "FeatureCollection",
"name": "Тц",
"crs": { "type": "name", "properties": { "name": "urn:ogc:def:crs:OGC:1.3:CRS84" } },
"features": [
{ "type": "Feature", "properties": { "full_id": "n1545549371", "osm_id": "1545549371", "osm_type": "node", "shop": "department_store", "level": null, "entrance": null, "operator": "Пельмондо", "opening_hours": "Mo-Fr 09:00-17:00", "name:ru": "Пельмондо", "name": "Пельмондо", "contact:vk": "https://vk.com/pelmondocafe", "contact:phone": "+7 921 6463731", "contact:instagram": "https://instagram.com/cafe_pelmondo", "contact:email": "pelmondo@bk.ru", "check_date": "2025-05-14", "amenity": "cafe" }, "geometry": { "type": "Point", "coordinates": [ 30.3096374, 59.9154243 ] } },
{ "type": "Feature", "properties": { "full_id": null, "osm_id": null, "osm_type": null, "shop": null, "level": null, "entrance": null, "operator": null, "opening_hours": null, "name:ru": null, "name": null, "contact:vk": null, "contact:phone": null, "contact:instagram": null, "contact:email": null, "check_date": null, "amenity": null }, "geometry": { "type": "Point", "coordinates": [ 30.348927600480419, 59.914682830884558 ] } },
{ "type": "Feature", "properties": { "full_id": null, "osm_id": null, "osm_type": null, "shop": null, "level": null, "entrance": null, "operator": null, "opening_hours": null, "name:ru": null, "name": null, "contact:vk": null, "contact:phone": null, "contact:instagram": null, "contact:email": null, "check_date": null, "amenity": null }, "geometry": { "type": "Point", "coordinates": [ 30.338927245941715, 59.919052222750608 ] } },
{ "type": "Feature", "properties": { "full_id": null, "osm_id": null, "osm_type": null, "shop": null, "level": null, "entrance": null, "operator": null, "opening_hours": null, "name:ru": null, "name": null, "contact:vk": null, "contact:phone": null, "contact:instagram": null, "contact:email": null, "check_date": null, "amenity": null }, "geometry": { "type": "Point", "coordinates": [ 30.307268369541138, 59.907524363296169 ] } },
{ "type": "Feature", "properties": { "full_id": null, "osm_id": null, "osm_type": null, "shop": null, "level": null, "entrance": null, "operator": null, "opening_hours": null, "name:ru": null, "name": null, "contact:vk": null, "contact:phone": null, "contact:instagram": null, "contact:email": null, "check_date": null, "amenity": null }, "geometry": { "type": "Point", "coordinates": [ 30.32021000482651, 59.925163045188249 ] } },
{ "type": "Feature", "properties": { "full_id": null, "osm_id": null, "osm_type": null, "shop": null, "level": null, "entrance": null, "operator": null, "opening_hours": null, "name:ru": null, "name": null, "contact:vk": null, "contact:phone": null, "contact:instagram": null, "contact:email": null, "check_date": null, "amenity": null }, "geometry": { "type": "Point", "coordinates": [ 30.320798260975845, 59.926288600268542 ] } }
]
}
